MANIFEST.in
setup.py
survey_data.xml
survey_demo.xml
survey_report.xml
survey_view.xml
./__init__.py
./__openerp__.py
./survey.py
./report/__init__.py
./report/survey_analysis_report.py
./report/survey_browse_response.py
./report/survey_form.py
./wizard/__init__.py
./wizard/survey_answer.py
./wizard/survey_browse_answer.py
./wizard/survey_print.py
./wizard/survey_print_answer.py
./wizard/survey_print_statistics.py
./wizard/survey_selection.py
./wizard/survey_send_invitation.py
i18n/ar.po
i18n/bg.po
i18n/ca.po
i18n/cs.po
i18n/da.po
i18n/de.po
i18n/es.po
i18n/es_CR.po
i18n/es_MX.po
i18n/es_VE.po
i18n/et.po
i18n/fi.po
i18n/fr.po
i18n/gl.po
i18n/hr.po
i18n/hu.po
i18n/it.po
i18n/ja.po
i18n/mk.po
i18n/mn.po
i18n/nl.po
i18n/pl.po
i18n/pt.po
i18n/pt_BR.po
i18n/ro.po
i18n/ru.po
i18n/sl.po
i18n/sr.po
i18n/sr@latin.po
i18n/survey.pot
i18n/sv.po
i18n/tr.po
i18n/zh_CN.po
images/survey_answers.jpeg
images/survey_pages.jpeg
images/surveys.jpeg
openerp_survey.egg-info/PKG-INFO
openerp_survey.egg-info/SOURCES.txt
openerp_survey.egg-info/dependency_links.txt
openerp_survey.egg-info/requires.txt
openerp_survey.egg-info/top_level.txt
security/ir.model.access.csv
security/survey_security.xml
specification/survey.png
specification/survey_page.png
specification/survey_question.png
specification/survey_response.png
test/draft2open2close_request.yml
test/draft2open2close_survey.yml
test/survey_question_type.yml
test/survey_report.yml
wizard/survey_answer.xml
wizard/survey_browse_answer.xml
wizard/survey_print.xml
wizard/survey_print_answer.xml
wizard/survey_print_statistics.xml
wizard/survey_selection.xml
wizard/survey_send_invitation.xml